<List>
  <Author>IFS RnD</Author>
  <Component>FNDBAS</Component>
  <LastModified>2015-08-06-13.24.16</LastModified>
  <Locked>true</Locked>
  <ColumnSpan>4</ColumnSpan>
  <Title>IN-MEMORY PARAMETERS</Title>
  <Background>#FF0087C1</Background>
  <Name>InMemory System Parameters</Name>
  <ID>06a8a5e9-2d28-4cd5-8b5d-9551f0b32409</ID>
  <DataSourceId>137b4b82-2736-452f-bd89-2df392cb1660</DataSourceId>
  <ColumnMapping>
    <MappedColumns>
      <MappedColumn>
        <Column>Name</Column>
        <Name>Name</Name>
        <DisplayName>Name</DisplayName>
        <Width>80</Width>
        <NavigateTarget>Name</NavigateTarget>
        <ConditionalFormats />
      </MappedColumn>
      <MappedColumn>
        <Column>Value</Column>
        <Name>Value</Name>
        <DisplayName>Value</DisplayName>
        <NavigateTarget>Value</NavigateTarget>
        <ConditionalFormats />
      </MappedColumn>
    </MappedColumns>
  </ColumnMapping>
</List>